{
  "$schema": "./custom_words.schema.json",
  "remède": {
    "synonyms": [
      "acupuncture",
      "électuaire",
      "émulsion",
      "antidote",
      "épithème",
      "bain",
      "baume",
      "biais",
      "bouillon",
      "calmant",
      "cataplasme",
      "cautère",
      "charme",
      "compresse",
      "confection",
      "contrepoison",
      "cure",
      "diète",
      "douche",
      "drogue",
      "emplâtre",
      "enveloppement",
      "expédient",
      "friction",
      "fumigation",
      "gargarisme",
      "grog",
      "implantation",
      "infusion",
      "inhalation",
      "injection",
      "instillation",
      "insufflation",
      "lavement",
      "médecine",
      "médicament",
      "médication",
      "manoeuvre",
      "mithridate",
      "moyen",
      "onguent",
      "orviétan",
      "palliatif",
      "panacée",
      "pansement",
      "parade",
      "perfusion",
      "piqûre",
      "placebo",
      "pommade",
      "ponction",
      "potion",
      "préparatif",
      "préparation",
      "préservatif",
      "purgation",
      "purge",
      "rééducation",
      "régime",
      "recette",
      "recours",
      "refuge",
      "relaxation",
      "ressource",
      "saignée",
      "sérum",
      "sinapisme",
      "solution",
      "soulagement",
      "spécialité",
      "spécifique",
      "suralimentation",
      "thérapeutique",
      "thériaque",
      "tisane",
      "topique",
      "traitement",
      "transfusion"
    ],
    "antonyms": [
      "embrocation",
      "expédient",
      "mal",
      "maladie"
    ],
    "etymologies": [
      "Du latin <i>remĕdium</i>."
    ],
    "definitions": [
      {
        "gender": "",
        "nature": "Nom propre",
        "explanations": [
          "(Informatique) Dictionnaire libre multiplateforme qui a pour objectif de remplacer Antidote."
        ],
        "examples": [
          {
            "content": "Tu connais pas <b>Remède</b> ? C'est le meilleur dictionnaire mobile !",
            "sources": "Un utilisateur de Remède, 2024"
          },
          {
            "content": "<b>Remède</b> mérite une <i>star</i> sur Github !",
            "sources": "Un utilisateur de Remède, 2024"
          }
        ],
        "plurals": []
      },
      {
        "gender": "masculin",
        "nature": "Nom commun",
        "explanations": [
          "(Médecine) Substance qui sert à guérir un mal ou une maladie. ",
          "(Sens figuré) Ce qui sert à guérir les maladies de l’âme. ",
          "(Sens figuré) Ce qui sert à prévenir, surmonter ou faire cesser un malheur, un inconvénient ou une disgrâce. ",
          "(En particulier) Lavement. "
        ],
        "examples": [
          {
            "content": "<i>Le suc d'une certaine plante appelée par les Caraïbes </i>touloula<i>, et par les Français </i>herbes aux flèches<i>, est, dit-on, le seul <b>remède</b> contre les plaies faites par les flèches empoisonnées avec le suc de mancenilier.</i> ",
            "sources": "(R. P. Jean-Baptiste Labat, <i>Voyages aux iles françaises de l'Amérique</i>, nouvelle édition d'après celle de 1722, Paris&#160;: chez Lefebvre &amp; chez A.-J. Ducollet, 1831, page 75)"
          },
          {
            "content": "<i>Ce fut M. de Chalvet-Rochemonteix qui apprit aux paysans à se prémunir contre les ravages de la carie dans les grains par le sulfatage de la semence, dont les résultats furent souverains. Le mal cessa avec l’application de ce <b>remède</b>.</i> ",
            "sources": "(Abbé Henri-Dominique Larrondo, <i>Monographie de la commune de Merville (Haute-Garonne)</i>, dans <i>Monographies de communes</i>, concours ouvert en 1897 par la Société des agriculteurs de France, Paris &amp; Lille&#160;: J. Lefort - A. Taffin-Lefort, successeur, 1898, page 96)"
          },
          {
            "content": "<i>Et, s’il acceptait qu’on le soignât, il refusait rudement tout <b>remède</b>, dans le doute où il était tombé de la médecine.</i> ",
            "sources": "(Émile Zola, <i>Le Docteur Pascal</i>, G. Charpentier, 1893, chapitre VI)"
          }
        ],
        "plurals": [
          {
            "label": "",
            "singular": "remède",
            "plural": "remèdes"
          }
        ]
      }
    ],
    "sources": [
      "fr_wik",
      "antonyme_org",
      "synonymo_fr"
    ],
    "phoneme": "/ʁəmɛd/",
    "conjugations": {}
  }
}
